telegram_bot/__init__.py
telegram_bot/apps.py
telegram_bot/checks.py
telegram_bot/defaults.py
telegram_bot/redis.py
telegram_bot/settings.py
telegram_bot/signals.py
telegram_bot/telegram_bot.py
telegram_bot/management/__init__.py
telegram_bot/management/commands/__init__.py
telegram_bot/management/commands/start_tgbot.py
django_redis_aiogram-1.0.8.dist-info/LICENSE
django_redis_aiogram-1.0.8.dist-info/METADATA
django_redis_aiogram-1.0.8.dist-info/WHEEL
django_redis_aiogram-1.0.8.dist-info/top_level.txt
django_redis_aiogram-1.0.8.dist-info/RECORD
