Metadata-Version: 2.1
Name: django-redis-aiogram
Version: 1.0.8
Summary: Running aiogram in neighbor container, sending messages to telegram via redis
Home-page: https://github.com/CorneiZeR/django-redis-aiogram
Author: Oleksii Kolosiuk
Author-email: kolosyuk1@gmail.com
License: MIT
Keywords: django redis aiogram docker
Classifier: Development Status :: 5 - Production/Stable
Classifier: Intended Audience :: Developers
Classifier: License :: OSI Approved :: MIT License
Classifier: Topic :: Software Development :: Libraries :: Python Modules
Classifier: Programming Language :: Python
Classifier: Programming Language :: Python :: 3
Classifier: Framework :: Django
Classifier: Framework :: Django :: 4
Classifier: Framework :: Django :: 5.0
Requires-Python: >=3.8
License-File: LICENSE
Requires-Dist: django >=4
Requires-Dist: redis >=4.6
Requires-Dist: aiogram >=3.0.0
